setup.py
arbetsformedlingen/__init__.py
arbetsformedlingen/arbetsformedlingen.py
arbetsformedlingen.egg-info/PKG-INFO
arbetsformedlingen.egg-info/SOURCES.txt
arbetsformedlingen.egg-info/dependency_links.txt
arbetsformedlingen.egg-info/requires.txt
arbetsformedlingen.egg-info/top_level.txt