Metadata-Version: 1.1
Name: arbetsformedlingen
Version: 0.1.0
Summary: Wrapper for http://api.arbetsformedlingen.se/
Home-page: https://github.com/willandskill/arbetsformedlingen
Author: Petter Nyman
Author-email: petter.nyman@willandskill.se
License: BSD licence
Download-URL: https://github.com/willandskill/arbetsformedlingen/archive/v0.0.3.tar.gz
Platform: UNKNOWN
